fecon236/__init__.py
fecon236/core.py
fecon236/tool.py
fecon236/top.py
fecon236/boots/__init__.py
fecon236/boots/bootstrap.py
fecon236/dst/__init__.py
fecon236/dst/gaussmix.py
fecon236/econ/__init__.py
fecon236/econ/infl.py
fecon236/futures/__init__.py
fecon236/futures/cftc.py
fecon236/host/__init__.py
fecon236/host/_ex_Quandl.py
fecon236/host/fred.py
fecon236/host/hostess.py
fecon236/host/qdl.py
fecon236/host/stock.py
fecon236/host/tmp_289_Quandl.py
fecon236/math/__init__.py
fecon236/math/matrix.py
fecon236/ml/__init__.py
fecon236/ml/learn.py
fecon236/oc/__init__.py
fecon236/oc/optimize.py
fecon236/parse/__init__.py
fecon236/parse/sec.py
fecon236/prob/__init__.py
fecon236/prob/sim.py
fecon236/prtf/__init__.py
fecon236/prtf/boltzmann.py
fecon236/rates/__init__.py
fecon236/rates/credit.py
fecon236/rates/fedfunds.py
fecon236/tsa/__init__.py
fecon236/tsa/holtwinters.py
fecon236/util/__init__.py
fecon236/util/group.py
fecon236/util/system.py
fecon236/visual/__init__.py
fecon236/visual/plots.py
fecon236-10.8.0.dist-info/METADATA
fecon236-10.8.0.dist-info/RECORD
fecon236-10.8.0.dist-info/WHEEL
fecon236-10.8.0.dist-info/top_level.txt
