Metadata-Version: 2.1
Name: fecon236
Version: 10.8.0
Summary: Tools for financial economics
Home-page: https://github.com/MathSci/fecon236
Author: Mathematical Sciences Group
Author-email: MathSci-github@googlegroups.com
License: BSD
Project-URL: Source, https://github.com/MathSci/fecon236
Project-URL: Notebooks, https://github.com/rsvp/fecon235/tree/master/nb
Project-URL: Installation, https://github.com/MathSci/fecon236/blob/develop/docs/READ/fe-10_Install.md
Project-URL: License, https://github.com/MathSci/fecon236/blob/master/LICENSE.md
Project-URL: Require, https://github.com/MathSci/fecon236/blob/develop/require.txt
Project-URL: Documentation, https://github.com/MathSci/fecon236/tree/develop/docs
Project-URL: Tracker, https://github.com/MathSci/fecon236/projects/3
Project-URL: Issues, https://github.com/MathSci/fecon236/issues
Keywords: finance economics statistics econometrics pandas jupyter
Platform: UNKNOWN
Classifier: Development Status :: 5 - Production/Stable
Classifier: License :: OSI Approved :: BSD License
Classifier: Topic :: Scientific/Engineering
Classifier: Topic :: Office/Business :: Financial :: Investment
Classifier: Intended Audience :: Science/Research
Classifier: Intended Audience :: Financial and Insurance Industry
Classifier: Natural Language :: English
Classifier: Programming Language :: Python
Classifier: Programming Language :: Python :: 2
Classifier: Programming Language :: Python :: 2.7
Classifier: Programming Language :: Python :: 3
Classifier: Programming Language :: Python :: 3.4
Classifier: Programming Language :: Python :: Implementation :: CPython
Requires-Python: >=2.7.0
